{
	"name": "Styncy (dark)",
	"type": "dark",
	"colors": {
		"foreground": "#AC95B5",
		"errorForeground": "#B040E9",
		"focusBorder": "#af95b920",
		"selection.background": "#af95b950",
		"widget.shadow": "#18071F",
		"input.background": "#432e51",
		"input.foreground": "#F0ECF2",
		"inputOption.activeBorder": "#B040E9",
		"input.placeholderForeground": "#AF95B9",
		"inputValidation.infoBackground": "#2C1437",
		"inputValidation.infoBorder": "#b040e9",
		"inputValidation.warningBackground": "#2C1437",
		"inputValidation.warningBorder": "#ff9f2e",
		"inputValidation.errorBackground": "#2C1437",
		"inputValidation.errorBorder": "#fc644d",
		"dropdown.background": "#432e51",
		"list.focusBackground": "#18071F",
		"list.activeSelectionBackground": "#AF95B980",
		"list.inactiveSelectionBackground": "#50395470",
		"list.inactiveFocusBackground": "#AF95B950",
		"list.hoverBackground": "#200924",
		"list.dropBackground": "#50395470",
		"pickerGroup.border": "#432e51",
		"button.background": "#B040E985",
		"button.hoverBackground": "#B040E9",
		"badge.background": "#B040E9",
		"scrollbar.shadow": "#25102e",
		"scrollbarSlider.background": "#AF95B977",
		"scrollbarSlider.hoverBackground": "#AF95B9aa",
		"scrollbarSlider.activeBackground": "#AF95B9cc",
		"editor.background": "#2C1437",
		"editor.foreground": "#f0ecf2",
		"editorWidget.background": "#25102e",
		"editor.selectionBackground": "#af95b950",
		"editor.selectionHighlightBackground": "#af95b950",
		"editor.findMatchBackground": "#B040E950",
		"editor.findMatchHighlightBackground": "#B040E975",
		"editor.hoverHighlightBackground": "#af95b950",
		"editorHoverWidget.background": "#25102e",
		"editorHoverWidget.border": "#25102e",
		"editorLink.activeForeground": "#B040E9",
		"diffEditor.insertedTextBackground": "#a5f69c20",
		"diffEditor.removedTextBackground": "#fc644d20",
		"merge.currentHeaderBackground": "#AF95B9bb",
		"merge.currentContentBackground": "#AF95B940",
		"merge.incomingHeaderBackground": "#B040E9bb",
		"merge.incomingContentBackground": "#B040E940",
		"merge.border": "#B040E9",
		"editor.lineHighlightBackground": "#432e5185",
		"editor.lineHighlightBorder": "#4c315850",
		"editor.rangeHighlightBackground": "#432e51",
		"editorCursor.foreground": "#ffffff",
		"editorWhitespace.foreground": "#432e51",
		"editorIndentGuide.background": "#432e51",
		"editorLineNumber.foreground": "#432e51",
		"editorRuler.foreground": "#432e51",
		"editorCodeLens.foreground": "#AF95B980",
		"editorBracketMatch.background": "#25102e",
		"editorBracketMatch.border": "#AF95B9",
		"editorOverviewRuler.border": "#432e51",
		"editorError.foreground": "#fc644d",
		"editorWarning.foreground": "#ff9f2e",
		"editorSuggestWidget.background": "#25102e",
		"editorSuggestWidget.border": "#25102e",
		"editorSuggestWidget.selectedBackground": "#432e51",
		"editor.wordHighlightBackground": "#AF95B950",
		"editor.wordHighlightStrongBackground": "#AF95B950",
		"peekViewTitle.background": "#AF95B980",
		"peekViewTitleDescription.foreground": "#AF95B9",
		"peekView.border": "#432e51",
		"peekViewResult.background": "#50395470",
		"peekViewResult.selectionBackground": "#AF95B980",
		"peekViewEditor.background": "#50395470",
		"peekViewResult.matchHighlightBackground": "#B040E950",
		"peekViewEditor.matchHighlightBackground": "#B040E950",
		"tab.border": "#25102E",
		"tab.activeBackground": "#2C1437",
		"tab.activeForeground": "#F0ECF2",
		"tab.inactiveBackground": "#25102E",
		"tab.inactiveForeground": "#AF95B9",
		"editorGroup.background": "#25102e",
		"editorGroupHeader.tabsBackground": "#25102e",
		"editorGroup.dropBackground": "#25102e",
		"panel.background": "#25102e",
		"panelTitle.inactiveForeground": "#AF95B9",
		"panelTitle.activeBorder": "#af95b960",
		"panel.border": "#2c1437",
		"statusBar.background": "#18071F",
		"statusBar.foreground": "#F0ECF2AD",
		"statusBar.noFolderBackground": "#432e51",
		"statusBarItem.activeBackground": "#432e51",
		"statusBarItem.hoverBackground": "#432e5180",
		"statusBarItem.prominentBackground": "#432e51",
		"statusBarItem.prominentHoverBackground": "#25102e",
		"statusBar.debuggingBackground": "#B040E9",
		"statusBar.debuggingForeground": "#F0ECF2",
		"activityBar.background": "#18071F",
		"activityBar.foreground": "#AF95B9",
		"activityBar.dropBackground": "#B040E9",
		"sideBar.background": "#25102E",
		"sideBarSectionHeader.background": "#432e51",
		"sideBar.border": "#2c1437",
		"titleBar.activeBackground": "#25102e",
		"debugExceptionWidget.border": "#fc644d",
		"debugExceptionWidget.background": "#25102E",
		"debugToolBar.background": "#18071F",
		"walkThrough.embeddedEditorBackground": "#25102e",
		"editorGutter.modifiedBackground": "#B040E9",
		"editorGutter.addedBackground": "#45c758bb",
		"editorGutter.deletedBackground": "#c91e1ebb",
		"extensionButton.prominentBackground": "#B040E970",
		"extensionButton.prominentHoverBackground": "#B040E9",
		"activityBarBadge.background": "#B040E9",
		"list.highlightForeground": "#B040E9",
		"editorSuggestWidget.highlightForeground": "#B040E9",
		"textLink.foreground": "#B040E9",
		"progressBar.background": "#B040E9",
		"pickerGroup.foreground": "#B040E9",
		"tab.activeBorder": "#B040E9",
		"notificationLink.foreground": "#B040E9",
		"list.activeSelectionForeground": "#F0ECF2",
		"list.inactiveSelectionForeground": "#AC95B5"
	},
	"tokenColors": [
		{
			"settings": {
				"foreground": "#fcfcfaff",
				"background": "#2d2a2eff"
			}
		},
		{
			"scope": [
				"comment",
				"comment keyword",
				"comment markup.underline.link",
				"comment string",
				"comment punctuation.definition",
				"comment punctuation"
			],
			"settings": {
				"fontStyle": "italic",
				"foreground": "#727072"
			}
		},
		{
			"scope": "\n\t\tcomment storage.type\n\t",
			"settings": {
				"foreground": "#727072"
			}
		},
		{
			"scope": "\n\t\tcomment entity.name.type\n\t",
			"settings": {
				"foreground": "#c1c0c0"
			}
		},
		{
			"scope": [
				"comment variable",
				"comment variable.other"
			],
			"settings": {
				"foreground": "#c1c0c0"
			}
		},
		{
			"scope": "constant",
			"settings": {
				"foreground": "#ab9df2"
			}
		},
		{
			"scope": "constant.other",
			"settings": {
				"foreground": "#fcfcfa"
			}
		},
		{
			"scope": "constant.other.property",
			"settings": {
				"foreground": "#ab9df2"
			}
		},
		{
			"scope": "constant.numeric",
			"settings": {
				"foreground": "#ab9df2"
			}
		},
		{
			"scope": "constant.language",
			"settings": {
				"foreground": "#ab9df2"
			}
		},
		{
			"scope": "constant.character.escape",
			"settings": {
				"foreground": "#ab9df2"
			}
		},
		{
			"scope": "constant.numeric.line-number.find-in-files",
			"settings": {
				"foreground": "#5b595c"
			}
		},
		{
			"scope": "constant.numeric.line-number.match.find-in-files",
			"settings": {
				"foreground": "#ffd866"
			}
		},
		{
			"scope": "entity.name.section",
			"settings": {
				"foreground": "#ffd866"
			}
		},
		{
			"scope": "entity.name",
			"settings": {
				"foreground": "#a9dc76"
			}
		},
		{
			"scope": "entity.name.class",
			"settings": {
				"foreground": "#fcfcfa"
			}
		},
		{
			"scope": "entity.name.namespace",
			"settings": {
				"foreground": "#fcfcfa"
			}
		},
		{
			"scope": "entity.other.inherited-class",
			"settings": {
				"fontStyle": "italic",
				"foreground": "#78dce8"
			}
		},
		{
			"scope": "entity.name.function",
			"settings": {
				"foreground": "#a9dc76"
			}
		},
		{
			"scope": "entity.name.tag",
			"settings": {
				"foreground": "#ff6188"
			}
		},
		{
			"scope": "entity.other.attribute-name",
			"settings": {
				"fontStyle": "italic",
				"foreground": "#78dce8"
			}
		},
		{
			"scope": [
				"entity.other.attribute-name.class.css",
				"entity.other.attribute-name.parent-selector-suffix.css",
				"entity.other.attribute-name.parent-selector-suffix.css punctuation.definition.entity.css"
			],
			"settings": {
				"foreground": "#a9dc76"
			}
		},
		{
			"scope": "entity.other.attribute-name.id.css",
			"settings": {
				"foreground": "#fc9867"
			}
		},
		{
			"scope": "entity.other.attribute-name.pseudo-class.css",
			"settings": {
				"fontStyle": "italic",
				"foreground": "#78dce8"
			}
		},
		{
			"scope": [
				"entity.name.function",
				"support.function"
			],
			"settings": {
				"foreground": "#a9dc76"
			}
		},
		{
			"scope": "invalid",
			"settings": {
				"fontStyle": "italic"
			}
		},
		{
			"scope": "keyword",
			"settings": {
				"foreground": "#ff6188"
			}
		},
		{
			"scope": "keyword.control",
			"settings": {
				"foreground": "#ff6188"
			}
		},
		{
			"scope": "keyword.operator",
			"settings": {
				"foreground": "#ff6188"
			}
		},
		{
			"scope": "keyword.other.substitution",
			"settings": {
				"foreground": "#939293"
			}
		},
		{
			"scope": "\n\t\tkeyword.other.template.begin\n\t\tkeyword.other.template.end\n\t",
			"settings": {
				"foreground": "#ff6188"
			}
		},
		{
			"scope": [
				"keyword.operator.heading.restructuredtext",
				"keyword.operator.table.row.restructuredtext",
				"keyword.operator.table.data.restructuredtext"
			],
			"settings": {
				"foreground": "#939293"
			}
		},
		{
			"scope": "markup.italic",
			"settings": {
				"fontStyle": "italic"
			}
		},
		{
			"scope": "markup.bold",
			"settings": {
				"fontStyle": "bold"
			}
		},
		{
			"scope": "markup.heading",
			"settings": {
				"foreground": "#ffd866"
			}
		},
		{
			"scope": "markup.raw",
			"settings": {
				"foreground": "#fc9867"
			}
		},
		{
			"scope": "markup.underline",
			"settings": {
				"fontStyle": "underline"
			}
		},
		{
			"scope": "markup.underline.link",
			"settings": {
				"foreground": "#a9dc76"
			}
		},
		{
			"scope": "markup.inserted",
			"settings": {
				"foreground": "#a9dc76"
			}
		},
		{
			"scope": "markup.deleted",
			"settings": {
				"foreground": "#ff6188"
			}
		},
		{
			"scope": "markup.changed",
			"settings": {
				"foreground": "#ffd866"
			}
		},
		{
			"scope": "markup.ignored",
			"settings": {
				"foreground": "#939293"
			}
		},
		{
			"scope": "markup.untracked",
			"settings": {
				"foreground": "#939293"
			}
		},
		{
			"scope": "markup.quote",
			"settings": {
				"fontStyle": "italic"
			}
		},
		{
			"scope": [
				"meta.brace.round",
				"meta.brace.square",
				"meta.brace.curly",
				"meta.delimiter.comma.js",
				"meta.function-call.without-arguments.js",
				"meta.function-call.method.without-arguments.js"
			],
			"settings": {
				"foreground": "#939293"
			}
		},
		{
			"scope": [
				"meta.function-call",
				"meta.function-call.arguments meta.function-call"
			],
			"settings": {
				"foreground": "#a9dc76"
			}
		},
		{
			"scope": [
				"meta.function-call meta.function-call.arguments",
				"meta.function-call meta.arguments",
				"meta.function-call meta.group"
			],
			"settings": {
				"foreground": "#fcfcfa"
			}
		},
		{
			"scope": "meta.instance.constructor",
			"settings": {
				"foreground": "#a9dc76"
			}
		},
		{
			"scope": "meta.attribute-with-value.class string",
			"settings": {
				"foreground": "#a9dc76"
			}
		},
		{
			"scope": "meta.attribute-with-value.id string",
			"settings": {
				"foreground": "#fc9867"
			}
		},
		{
			"scope": [
				"source.json meta.structure.dictionary",
				"source.json meta.structure.dictionary meta.structure.dictionary.value meta.structure.dictionary",
				"source.json meta.structure.dictionary meta.structure.dictionary.value meta.structure.dictionary meta.structure.dictionary.value meta.structure.dictionary",
				"source.json meta.structure.dictionary meta.structure.dictionary.value meta.structure.dictionary meta.structure.dictionary.value meta.structure.dictionary meta.structure.dictionary.value meta.structure.dictionary",
				"source.json meta.structure.dictionary meta.structure.dictionary.value meta.structure.dictionary meta.structure.dictionary.value meta.structure.dictionary meta.structure.dictionary.value meta.structure.dictionary meta.structure.dictionary.value meta.structure.dictionary",
				"source.json meta.structure.dictionary meta.structure.dictionary.value meta.structure.dictionary meta.structure.dictionary.value meta.structure.dictionary meta.structure.dictionary.value meta.structure.dictionary meta.structure.dictionary.value meta.structure.dictionary meta.structure.dictionary.value meta.structure.dictionary",
				"source.json meta.structure.dictionary meta.structure.dictionary.value meta.structure.dictionary meta.structure.dictionary.value meta.structure.dictionary meta.structure.dictionary.value meta.structure.dictionary meta.structure.dictionary.value meta.structure.dictionary meta.structure.dictionary.value meta.structure.dictionary meta.structure.dictionary.value meta.structure.dictionary",
				"source.json meta.structure.dictionary meta.structure.dictionary.value meta.structure.dictionary meta.structure.dictionary.value meta.structure.dictionary meta.structure.dictionary.value meta.structure.dictionary meta.structure.dictionary.value meta.structure.dictionary meta.structure.dictionary.value meta.structure.dictionary meta.structure.dictionary.value meta.structure.dictionary meta.structure.dictionary.value meta.structure.dictionary",
				"source.json meta.structure.dictionary meta.structure.dictionary.value meta.structure.dictionary meta.structure.dictionary.value meta.structure.dictionary meta.structure.dictionary.value meta.structure.dictionary meta.structure.dictionary.value meta.structure.dictionary meta.structure.dictionary.value meta.structure.dictionary meta.structure.dictionary.value meta.structure.dictionary meta.structure.dictionary.value meta.structure.dictionary meta.structure.dictionary.value meta.structure.dictionary",
				"source.json meta.structure.dictionary meta.structure.dictionary.value meta.structure.dictionary meta.structure.dictionary.value meta.structure.dictionary meta.structure.dictionary.value meta.structure.dictionary meta.structure.dictionary.value meta.structure.dictionary meta.structure.dictionary.value meta.structure.dictionary meta.structure.dictionary.value meta.structure.dictionary meta.structure.dictionary.value meta.structure.dictionary meta.structure.dictionary.value meta.structure.dictionary meta.structure.dictionary.value meta.structure.dictionary",
				"source.json meta.structure.dictionary meta.structure.dictionary.value meta.structure.dictionary meta.structure.dictionary.value meta.structure.dictionary meta.structure.dictionary.value meta.structure.dictionary meta.structure.dictionary.value meta.structure.dictionary meta.structure.dictionary.value meta.structure.dictionary meta.structure.dictionary.value meta.structure.dictionary meta.structure.dictionary.value meta.structure.dictionary meta.structure.dictionary.value meta.structure.dictionary meta.structure.dictionary.value meta.structure.dictionary meta.structure.dictionary.value meta.structure.dictionary",
				"source.json meta.structure.dictionary meta.structure.dictionary.value meta.structure.dictionary meta.structure.dictionary.value meta.structure.dictionary meta.structure.dictionary.value meta.structure.dictionary meta.structure.dictionary.value meta.structure.dictionary meta.structure.dictionary.value meta.structure.dictionary meta.structure.dictionary.value meta.structure.dictionary meta.structure.dictionary.value meta.structure.dictionary meta.structure.dictionary.value meta.structure.dictionary meta.structure.dictionary.value meta.structure.dictionary meta.structure.dictionary.value meta.structure.dictionary meta.structure.dictionary.value meta.structure.dictionary",
				"source.json meta.structure.dictionary meta.structure.dictionary.value meta.structure.dictionary meta.structure.dictionary.value meta.structure.dictionary meta.structure.dictionary.value meta.structure.dictionary meta.structure.dictionary.value meta.structure.dictionary meta.structure.dictionary.value meta.structure.dictionary meta.structure.dictionary.value meta.structure.dictionary meta.structure.dictionary.value meta.structure.dictionary meta.structure.dictionary.value meta.structure.dictionary meta.structure.dictionary.value meta.structure.dictionary meta.structure.dictionary.value meta.structure.dictionary meta.structure.dictionary.value meta.structure.dictionary meta.structure.dictionary.value meta.structure.dictionary",
				"source.json meta.structure.dictionary meta.structure.dictionary.value meta.structure.dictionary meta.structure.dictionary.value meta.structure.dictionary meta.structure.dictionary.value meta.structure.dictionary meta.structure.dictionary.value meta.structure.dictionary meta.structure.dictionary.value meta.structure.dictionary meta.structure.dictionary.value meta.structure.dictionary meta.structure.dictionary.value meta.structure.dictionary meta.structure.dictionary.value meta.structure.dictionary meta.structure.dictionary.value meta.structure.dictionary meta.structure.dictionary.value meta.structure.dictionary meta.structure.dictionary.value meta.structure.dictionary meta.structure.dictionary.value meta.structure.dictionary meta.structure.dictionary.value meta.structure.dictionary",
				"source.json meta.structure.dictionary meta.structure.dictionary.value meta.structure.dictionary meta.structure.dictionary.value meta.structure.dictionary meta.structure.dictionary.value meta.structure.dictionary meta.structure.dictionary.value meta.structure.dictionary meta.structure.dictionary.value meta.structure.dictionary meta.structure.dictionary.value meta.structure.dictionary meta.structure.dictionary.value meta.structure.dictionary meta.structure.dictionary.value meta.structure.dictionary meta.structure.dictionary.value meta.structure.dictionary meta.structure.dictionary.value meta.structure.dictionary meta.structure.dictionary.value meta.structure.dictionary meta.structure.dictionary.value meta.structure.dictionary meta.structure.dictionary.value meta.structure.dictionary meta.structure.dictionary.value meta.structure.dictionary",
				"source.json meta.structure.dictionary meta.structure.dictionary.value meta.structure.dictionary meta.structure.dictionary.value meta.structure.dictionary meta.structure.dictionary.value meta.structure.dictionary meta.structure.dictionary.value meta.structure.dictionary meta.structure.dictionary.value meta.structure.dictionary meta.structure.dictionary.value meta.structure.dictionary meta.structure.dictionary.value meta.structure.dictionary meta.structure.dictionary.value meta.structure.dictionary meta.structure.dictionary.value meta.structure.dictionary meta.structure.dictionary.value meta.structure.dictionary meta.structure.dictionary.value meta.structure.dictionary meta.structure.dictionary.value meta.structure.dictionary meta.structure.dictionary.value meta.structure.dictionary meta.structure.dictionary.value meta.structure.dictionary meta.structure.dictionary.value meta.structure.dictionary",
				"source.json meta.structure.dictionary string",
				"source.json meta.structure.dictionary meta.structure.dictionary.value meta.structure.dictionary string",
				"source.json meta.structure.dictionary meta.structure.dictionary.value meta.structure.dictionary meta.structure.dictionary.value meta.structure.dictionary string",
				"source.json meta.structure.dictionary meta.structure.dictionary.value meta.structure.dictionary meta.structure.dictionary.value meta.structure.dictionary meta.structure.dictionary.value meta.structure.dictionary string",
				"source.json meta.structure.dictionary meta.structure.dictionary.value meta.structure.dictionary meta.structure.dictionary.value meta.structure.dictionary meta.structure.dictionary.value meta.structure.dictionary meta.structure.dictionary.value meta.structure.dictionary string",
				"source.json meta.structure.dictionary meta.structure.dictionary.value meta.structure.dictionary meta.structure.dictionary.value meta.structure.dictionary meta.structure.dictionary.value meta.structure.dictionary meta.structure.dictionary.value meta.structure.dictionary meta.structure.dictionary.value meta.structure.dictionary string",
				"source.json meta.structure.dictionary meta.structure.dictionary.value meta.structure.dictionary meta.structure.dictionary.value meta.structure.dictionary meta.structure.dictionary.value meta.structure.dictionary meta.structure.dictionary.value meta.structure.dictionary meta.structure.dictionary.value meta.structure.dictionary meta.structure.dictionary.value meta.structure.dictionary string",
				"source.json meta.structure.dictionary meta.structure.dictionary.value meta.structure.dictionary meta.structure.dictionary.value meta.structure.dictionary meta.structure.dictionary.value meta.structure.dictionary meta.structure.dictionary.value meta.structure.dictionary meta.structure.dictionary.value meta.structure.dictionary meta.structure.dictionary.value meta.structure.dictionary meta.structure.dictionary.value meta.structure.dictionary string",
				"source.json meta.structure.dictionary meta.structure.dictionary.value meta.structure.dictionary meta.structure.dictionary.value meta.structure.dictionary meta.structure.dictionary.value meta.structure.dictionary meta.structure.dictionary.value meta.structure.dictionary meta.structure.dictionary.value meta.structure.dictionary meta.structure.dictionary.value meta.structure.dictionary meta.structure.dictionary.value meta.structure.dictionary meta.structure.dictionary.value meta.structure.dictionary string",
				"source.json meta.structure.dictionary meta.structure.dictionary.value meta.structure.dictionary meta.structure.dictionary.value meta.structure.dictionary meta.structure.dictionary.value meta.structure.dictionary meta.structure.dictionary.value meta.structure.dictionary meta.structure.dictionary.value meta.structure.dictionary meta.structure.dictionary.value meta.structure.dictionary meta.structure.dictionary.value meta.structure.dictionary meta.structure.dictionary.value meta.structure.dictionary meta.structure.dictionary.value meta.structure.dictionary string",
				"source.json meta.structure.dictionary meta.structure.dictionary.value meta.structure.dictionary meta.structure.dictionary.value meta.structure.dictionary meta.structure.dictionary.value meta.structure.dictionary meta.structure.dictionary.value meta.structure.dictionary meta.structure.dictionary.value meta.structure.dictionary meta.structure.dictionary.value meta.structure.dictionary meta.structure.dictionary.value meta.structure.dictionary meta.structure.dictionary.value meta.structure.dictionary meta.structure.dictionary.value meta.structure.dictionary meta.structure.dictionary.value meta.structure.dictionary string",
				"source.json meta.structure.dictionary meta.structure.dictionary.value meta.structure.dictionary meta.structure.dictionary.value meta.structure.dictionary meta.structure.dictionary.value meta.structure.dictionary meta.structure.dictionary.value meta.structure.dictionary meta.structure.dictionary.value meta.structure.dictionary meta.structure.dictionary.value meta.structure.dictionary meta.structure.dictionary.value meta.structure.dictionary meta.structure.dictionary.value meta.structure.dictionary meta.structure.dictionary.value meta.structure.dictionary meta.structure.dictionary.value meta.structure.dictionary meta.structure.dictionary.value meta.structure.dictionary string",
				"source.json meta.structure.dictionary meta.structure.dictionary.value meta.structure.dictionary meta.structure.dictionary.value meta.structure.dictionary meta.structure.dictionary.value meta.structure.dictionary meta.structure.dictionary.value meta.structure.dictionary meta.structure.dictionary.value meta.structure.dictionary meta.structure.dictionary.value meta.structure.dictionary meta.structure.dictionary.value meta.structure.dictionary meta.structure.dictionary.value meta.structure.dictionary meta.structure.dictionary.value meta.structure.dictionary meta.structure.dictionary.value meta.structure.dictionary meta.structure.dictionary.value meta.structure.dictionary meta.structure.dictionary.value meta.structure.dictionary string",
				"source.json meta.structure.dictionary meta.structure.dictionary.value meta.structure.dictionary meta.structure.dictionary.value meta.structure.dictionary meta.structure.dictionary.value meta.structure.dictionary meta.structure.dictionary.value meta.structure.dictionary meta.structure.dictionary.value meta.structure.dictionary meta.structure.dictionary.value meta.structure.dictionary meta.structure.dictionary.value meta.structure.dictionary meta.structure.dictionary.value meta.structure.dictionary meta.structure.dictionary.value meta.structure.dictionary meta.structure.dictionary.value meta.structure.dictionary meta.structure.dictionary.value meta.structure.dictionary meta.structure.dictionary.value meta.structure.dictionary meta.structure.dictionary.value meta.structure.dictionary string",
				"source.json meta.structure.dictionary meta.structure.dictionary.value meta.structure.dictionary meta.structure.dictionary.value meta.structure.dictionary meta.structure.dictionary.value meta.structure.dictionary meta.structure.dictionary.value meta.structure.dictionary meta.structure.dictionary.value meta.structure.dictionary meta.structure.dictionary.value meta.structure.dictionary meta.structure.dictionary.value meta.structure.dictionary meta.structure.dictionary.value meta.structure.dictionary meta.structure.dictionary.value meta.structure.dictionary meta.structure.dictionary.value meta.structure.dictionary meta.structure.dictionary.value meta.structure.dictionary meta.structure.dictionary.value meta.structure.dictionary meta.structure.dictionary.value meta.structure.dictionary meta.structure.dictionary.value meta.structure.dictionary string",
				"source.json meta.structure.dictionary meta.structure.dictionary.value meta.structure.dictionary meta.structure.dictionary.value meta.structure.dictionary meta.structure.dictionary.value meta.structure.dictionary meta.structure.dictionary.value meta.structure.dictionary meta.structure.dictionary.value meta.structure.dictionary meta.structure.dictionary.value meta.structure.dictionary meta.structure.dictionary.value meta.structure.dictionary meta.structure.dictionary.value meta.structure.dictionary meta.structure.dictionary.value meta.structure.dictionary meta.structure.dictionary.value meta.structure.dictionary meta.structure.dictionary.value meta.structure.dictionary meta.structure.dictionary.value meta.structure.dictionary meta.structure.dictionary.value meta.structure.dictionary meta.structure.dictionary.value meta.structure.dictionary meta.structure.dictionary.value meta.structure.dictionary string"
			],
			"settings": {
				"foreground": "#fcfcfa"
			}
		},
		{
			"scope": [
				"source.json meta.structure.dictionary.value string",
				"source.json meta.structure.dictionary.value meta.structure.dictionary meta.structure.dictionary.value string",
				"source.json meta.structure.dictionary.value meta.structure.dictionary meta.structure.dictionary.value meta.structure.dictionary meta.structure.dictionary.value string",
				"source.json meta.structure.dictionary.value meta.structure.dictionary meta.structure.dictionary.value meta.structure.dictionary meta.structure.dictionary.value meta.structure.dictionary meta.structure.dictionary.value string",
				"source.json meta.structure.dictionary.value meta.structure.dictionary meta.structure.dictionary.value meta.structure.dictionary meta.structure.dictionary.value meta.structure.dictionary meta.structure.dictionary.value meta.structure.dictionary meta.structure.dictionary.value string",
				"source.json meta.structure.dictionary.value meta.structure.dictionary meta.structure.dictionary.value meta.structure.dictionary meta.structure.dictionary.value meta.structure.dictionary meta.structure.dictionary.value meta.structure.dictionary meta.structure.dictionary.value meta.structure.dictionary meta.structure.dictionary.value string",
				"source.json meta.structure.dictionary.value meta.structure.dictionary meta.structure.dictionary.value meta.structure.dictionary meta.structure.dictionary.value meta.structure.dictionary meta.structure.dictionary.value meta.structure.dictionary meta.structure.dictionary.value meta.structure.dictionary meta.structure.dictionary.value meta.structure.dictionary meta.structure.dictionary.value string",
				"source.json meta.structure.dictionary.value meta.structure.dictionary meta.structure.dictionary.value meta.structure.dictionary meta.structure.dictionary.value meta.structure.dictionary meta.structure.dictionary.value meta.structure.dictionary meta.structure.dictionary.value meta.structure.dictionary meta.structure.dictionary.value meta.structure.dictionary meta.structure.dictionary.value meta.structure.dictionary meta.structure.dictionary.value string",
				"source.json meta.structure.dictionary.value meta.structure.dictionary meta.structure.dictionary.value meta.structure.dictionary meta.structure.dictionary.value meta.structure.dictionary meta.structure.dictionary.value meta.structure.dictionary meta.structure.dictionary.value meta.structure.dictionary meta.structure.dictionary.value meta.structure.dictionary meta.structure.dictionary.value meta.structure.dictionary meta.structure.dictionary.value meta.structure.dictionary meta.structure.dictionary.value string",
				"source.json meta.structure.dictionary.value meta.structure.dictionary meta.structure.dictionary.value meta.structure.dictionary meta.structure.dictionary.value meta.structure.dictionary meta.structure.dictionary.value meta.structure.dictionary meta.structure.dictionary.value meta.structure.dictionary meta.structure.dictionary.value meta.structure.dictionary meta.structure.dictionary.value meta.structure.dictionary meta.structure.dictionary.value meta.structure.dictionary meta.structure.dictionary.value meta.structure.dictionary meta.structure.dictionary.value string",
				"source.json meta.structure.dictionary.value meta.structure.dictionary meta.structure.dictionary.value meta.structure.dictionary meta.structure.dictionary.value meta.structure.dictionary meta.structure.dictionary.value meta.structure.dictionary meta.structure.dictionary.value meta.structure.dictionary meta.structure.dictionary.value meta.structure.dictionary meta.structure.dictionary.value meta.structure.dictionary meta.structure.dictionary.value meta.structure.dictionary meta.structure.dictionary.value meta.structure.dictionary meta.structure.dictionary.value meta.structure.dictionary meta.structure.dictionary.value string",
				"source.json meta.structure.dictionary.value meta.structure.dictionary meta.structure.dictionary.value meta.structure.dictionary meta.structure.dictionary.value meta.structure.dictionary meta.structure.dictionary.value meta.structure.dictionary meta.structure.dictionary.value meta.structure.dictionary meta.structure.dictionary.value meta.structure.dictionary meta.structure.dictionary.value meta.structure.dictionary meta.structure.dictionary.value meta.structure.dictionary meta.structure.dictionary.value meta.structure.dictionary meta.structure.dictionary.value meta.structure.dictionary meta.structure.dictionary.value meta.structure.dictionary meta.structure.dictionary.value string",
				"source.json meta.structure.dictionary.value meta.structure.dictionary meta.structure.dictionary.value meta.structure.dictionary meta.structure.dictionary.value meta.structure.dictionary meta.structure.dictionary.value meta.structure.dictionary meta.structure.dictionary.value meta.structure.dictionary meta.structure.dictionary.value meta.structure.dictionary meta.structure.dictionary.value meta.structure.dictionary meta.structure.dictionary.value meta.structure.dictionary meta.structure.dictionary.value meta.structure.dictionary meta.structure.dictionary.value meta.structure.dictionary meta.structure.dictionary.value meta.structure.dictionary meta.structure.dictionary.value meta.structure.dictionary meta.structure.dictionary.value string",
				"source.json meta.structure.dictionary.value meta.structure.dictionary meta.structure.dictionary.value meta.structure.dictionary meta.structure.dictionary.value meta.structure.dictionary meta.structure.dictionary.value meta.structure.dictionary meta.structure.dictionary.value meta.structure.dictionary meta.structure.dictionary.value meta.structure.dictionary meta.structure.dictionary.value meta.structure.dictionary meta.structure.dictionary.value meta.structure.dictionary meta.structure.dictionary.value meta.structure.dictionary meta.structure.dictionary.value meta.structure.dictionary meta.structure.dictionary.value meta.structure.dictionary meta.structure.dictionary.value meta.structure.dictionary meta.structure.dictionary.value meta.structure.dictionary meta.structure.dictionary.value string",
				"source.json meta.structure.dictionary.value meta.structure.dictionary meta.structure.dictionary.value meta.structure.dictionary meta.structure.dictionary.value meta.structure.dictionary meta.structure.dictionary.value meta.structure.dictionary meta.structure.dictionary.value meta.structure.dictionary meta.structure.dictionary.value meta.structure.dictionary meta.structure.dictionary.value meta.structure.dictionary meta.structure.dictionary.value meta.structure.dictionary meta.structure.dictionary.value meta.structure.dictionary meta.structure.dictionary.value meta.structure.dictionary meta.structure.dictionary.value meta.structure.dictionary meta.structure.dictionary.value meta.structure.dictionary meta.structure.dictionary.value meta.structure.dictionary meta.structure.dictionary.value meta.structure.dictionary meta.structure.dictionary.value string",
				"source.json meta.structure.dictionary.value meta.structure.dictionary meta.structure.dictionary.value meta.structure.dictionary meta.structure.dictionary.value meta.structure.dictionary meta.structure.dictionary.value meta.structure.dictionary meta.structure.dictionary.value meta.structure.dictionary meta.structure.dictionary.value meta.structure.dictionary meta.structure.dictionary.value meta.structure.dictionary meta.structure.dictionary.value meta.structure.dictionary meta.structure.dictionary.value meta.structure.dictionary meta.structure.dictionary.value meta.structure.dictionary meta.structure.dictionary.value meta.structure.dictionary meta.structure.dictionary.value meta.structure.dictionary meta.structure.dictionary.value meta.structure.dictionary meta.structure.dictionary.value meta.structure.dictionary meta.structure.dictionary.value meta.structure.dictionary meta.structure.dictionary.value string"
			],
			"settings": {
				"foreground": "#ffd866"
			}
		},
		{
			"scope": "meta.object.member",
			"settings": {
				"foreground": "#fcfcfa"
			}
		},
		{
			"scope": "meta.property-list.css variable.other",
			"settings": {
				"foreground": "#fc9867"
			}
		},
		{
			"scope": [
				"entity.name.constant.preprocessor",
				"meta.preprocessor"
			],
			"settings": {
				"foreground": "#ab9df2"
			}
		},
		{
			"scope": "punctuation",
			"settings": {
				"foreground": "#939293"
			}
		},
		{
			"scope": "punctuation.definition.group",
			"settings": {
				"foreground": "#fcfcfa"
			}
		},
		{
			"scope": "punctuation.definition.comment",
			"settings": {
				"foreground": "#727072"
			}
		},
		{
			"scope": [
				"punctuation.definition.variable",
				"punctuation.definition.keyword.scss",
				"punctuation.definition.entity.css"
			],
			"settings": {
				"foreground": "#c1c0c0"
			}
		},
		{
			"scope": "punctuation.section.embedded",
			"settings": {
				"foreground": "#fc9867"
			}
		},
		{
			"scope": [
				"punctuation.template-string.element.begin",
				"punctuation.template-string.element.end",
				"string.quoted.template punctuation.definition.string.begin",
				"string.quoted.template punctuation.definition.string.end"
			],
			"settings": {
				"foreground": "#ff6188"
			}
		},
		{
			"scope": "source.scss",
			"settings": {
				"foreground": "#939293"
			}
		},
		{
			"scope": [
				"source.scss variable.other",
				"source.scss variable.scss",
				"source.css variable.other",
				"source.css variable.scss",
				"source.less variable.other",
				"source.less variable.other.less",
				"source.less variable.declaration.less"
			],
			"settings": {
				"fontStyle": "italic",
				"foreground": "#fc9867"
			}
		},
		{
			"scope": "storage",
			"settings": {
				"foreground": "#ff6188"
			}
		},
		{
			"scope": "storage.type",
			"settings": {
				"fontStyle": "italic",
				"foreground": "#78dce8"
			}
		},
		{
			"scope": "storage.type.function.arrow",
			"settings": {
				"fontStyle": "normal",
				"foreground": "#ff6188"
			}
		},
		{
			"scope": "storage.modifier",
			"settings": {
				"fontStyle": "italic",
				"foreground": "#ff6188"
			}
		},
		{
			"scope": "storage.class.restructuredtext.ref",
			"settings": {
				"foreground": "#ab9df2"
			}
		},
		{
			"scope": "string",
			"settings": {
				"foreground": "#ffd866"
			}
		},
		{
			"scope": "string.unquoted.label",
			"settings": {
				"foreground": "#fcfcfa"
			}
		},
		{
			"scope": "string source",
			"settings": {
				"foreground": "#fcfcfa"
			}
		},
		{
			"scope": "string source punctuation.section.embedded",
			"settings": {
				"foreground": "#939293"
			}
		},
		{
			"scope": [
				"string.other.link.title",
				"string.other.link.description"
			],
			"settings": {
				"foreground": "#ff6188"
			}
		},
		{
			"scope": "string.other.link.description.title",
			"settings": {
				"foreground": "#78dce8"
			}
		},
		{
			"scope": [
				"string.regexp punctuation.definition.string.begin",
				"string.regexp punctuation.definition.string.end"
			],
			"settings": {
				"foreground": "#ff6188"
			}
		},
		{
			"scope": [
				"string.other.ref",
				"string.other.restructuredtext.ref"
			],
			"settings": {
				"foreground": "#a9dc76"
			}
		},
		{
			"scope": "support.constant",
			"settings": {
				"foreground": "#78dce8"
			}
		},
		{
			"scope": "support.function",
			"settings": {
				"foreground": "#a9dc76"
			}
		},
		{
			"scope": [
				"support.type",
				"entity.name.type.object.console"
			],
			"settings": {
				"fontStyle": "italic",
				"foreground": "#78dce8"
			}
		},
		{
			"scope": "support.variable",
			"settings": {
				"foreground": "#78dce8"
			}
		},
		{
			"scope": "support.type.property-name",
			"settings": {
				"fontStyle": "normal",
				"foreground": "#fcfcfa"
			}
		},
		{
			"scope": "support.class",
			"settings": {
				"foreground": "#78dce8"
			}
		},
		{
			"scope": "text.find-in-files",
			"settings": {
				"foreground": "#fcfcfa"
			}
		},
		{
			"scope": [
				"variable",
				"variable.other"
			],
			"settings": {
				"foreground": "#fcfcfa"
			}
		},
		{
			"scope": [
				"variable.parameter",
				"parameters variable.function"
			],
			"settings": {
				"fontStyle": "italic",
				"foreground": "#fc9867"
			}
		},
		{
			"scope": [
				"variable.language",
				"variable.parameter.function.language.special.self.python"
			],
			"settings": {
				"fontStyle": "italic",
				"foreground": "#c1c0c0"
			}
		},
		{
			"scope": "variable.language.arguments",
			"settings": {
				"foreground": "#ab9df2"
			}
		},
		{
			"scope": "variable.other.class",
			"settings": {
				"foreground": "#78dce8"
			}
		},
		{
			"scope": "variable.other.constant",
			"settings": {
				"foreground": "#ab9df2"
			}
		},
		{
			"scope": "variable.other.member",
			"settings": {
				"foreground": "#fcfcfa"
			}
		},
		{
			"scope": "variable.function",
			"settings": {
				"foreground": "#a9dc76"
			}
		},
		{
			"scope": "variable.other.substitution",
			"settings": {
				"foreground": "#fc9867"
			}
		},
		{
			"scope": "token.info-token",
			"settings": {
				"foreground": "#6796e6"
			}
		},
		{
			"scope": "token.warn-token",
			"settings": {
				"foreground": "#cd9731"
			}
		},
		{
			"scope": "token.error-token",
			"settings": {
				"foreground": "#f44747"
			}
		},
		{
			"scope": "token.debug-token",
			"settings": {
				"foreground": "#b267e6"
			}
		}
	]
}